simsad/__init__.py
simsad/ces.py
simsad/chsld.py
simsad/clsc.py
simsad/cmd.py
simsad/demo.py
simsad/dispatch.py
simsad/eesad.py
simsad/home.py
simsad/msss.py
simsad/needs.py
simsad/nsa.py
simsad/pefsad.py
simsad/policy.py
simsad/prefs.py
simsad/prive.py
simsad/project.py
simsad/ri.py
simsad/rpa.py
simsad/tracker.py
simsad/data/calib_cmd.csv
simsad/data/gps.csv
simsad/data/hrs_ces.csv
simsad/data/hrs_csss_avd_home.csv
simsad/data/hrs_csss_avd_rpa.csv
simsad/data/hrs_csss_inf_avq_home.csv
simsad/data/hrs_csss_inf_avq_ri.csv
simsad/data/hrs_csss_inf_avq_rpa.csv
simsad/data/hrs_csss_inf_ri.csv
simsad/data/mnt_cmd.csv
simsad/data/nb_milieu_vie_init.csv
simsad/data/needs.csv
simsad/data/params_prefs_smaf.csv
simsad/data/pefsad_home.csv
simsad/data/pefsad_rpa.csv
simsad/data/pop-isq.csv
simsad/data/prob_ces.csv
simsad/data/prob_csss_avd_home.csv
simsad/data/prob_csss_avd_rpa.csv
simsad/data/prob_csss_inf_avq_home.csv
simsad/data/prob_csss_inf_avq_ri.csv
simsad/data/prob_csss_inf_avq_rpa.csv
simsad/data/prob_eval.csv
simsad/data/prob_iso-smaf.csv
simsad/data/prob_mensuelles_deces.csv
simsad/data/prob_mv_attente.csv
simsad/data/prob_mv_attente_ri.csv
simsad/data/registre_chsld.csv
simsad/data/registre_clsc.csv
simsad/data/registre_eesad.csv
simsad/data/registre_nsa.csv
simsad/data/registre_prive.csv
simsad/data/registre_ri.csv
simsad/data/registre_rpa.csv
simsad/data/transition_mensuelles_milieu_vie.csv
simsad_cjp-1.1.0.dist-info/LICENSE
simsad_cjp-1.1.0.dist-info/METADATA
simsad_cjp-1.1.0.dist-info/WHEEL
simsad_cjp-1.1.0.dist-info/top_level.txt
simsad_cjp-1.1.0.dist-info/RECORD
