Metadata-Version: 2.1
Name: simsad-cjp
Version: 1.1.0
Summary: Modele de projection du soutien à l'autonomie du Quebec
Home-page: https://cjp-models.github.io/SimSAD/
Author: Equipe CJP
Author-email: pierre-carl.michaud@hec.ca
Classifier: Programming Language :: Python :: 3
Classifier: License :: OSI Approved :: MIT License
Classifier: Operating System :: OS Independent
Requires-Python: >=3.9
License-File: LICENSE
Requires-Dist: pandas
Requires-Dist: numba (>=0.58)
Requires-Dist: numpy (>=1.24)
Requires-Dist: xlrd
Requires-Dist: xlsxwriter
